{
  "material": "Эмаль",
  "series": [
    {
      "title": "Л",
      "models": [
        {
          "title": "Л10",
          "dop": [{"title":"витраж с пескоструйным рисунком"},{"title":"витраж с глубоким матированием"}]
        },
        {
          "title": "Л11",
          "dop": [{"title":"витраж с пескоструйным рисунком"},{"title":"витраж с глубоким матированием"}]
        },
        {
          "title": "Л12*",
          "dop": [{"title":"витраж с пескоструйным рисунком"},{"title":"витраж с глубоким матированием"}]
        },
        {
          "title": "Л13",
          "dop": [{"title":"витраж с пескоструйным рисунком"},{"title":"витраж с глубоким матированием"}]
        },
        {
          "title": "Л13-Б",
          "dop": [
            {"title": "витраж на стекле Сатин, 6 мм, с фацетом с двух сторон"},
            {"title":"витраж с пескоструйным рисунком"},{"title":"витраж с глубоким матированием"}
          ]
        },
        {
          "title": "Л13-С",
          "dop": [
            {"title": "витраж на стекле Сатин, 6 мм, с фацетом с двух сторон"},
            {"title":"витраж с пескоструйным рисунком"},{"title":"витраж с глубоким матированием"}
          ]
        },
        {
          "title": "Л13-Ф",
          "dop": [
            {"title": "витраж на стекле Сатин, 6 мм, с фацетом с двух сторон"},
            {"title":"витраж с пескоструйным рисунком"},{"title":"витраж с глубоким матированием"}
          ]
        },
        {
          "title": "Л70",
          "dop": [{"title":"витраж с пескоструйным рисунком"},{"title":"витраж с глубоким матированием"}]
        },
        {
          "title": "Л71",
          "dop": [{"title":"витраж с пескоструйным рисунком"},{"title":"витраж с глубоким матированием"}]
        },
        {
          "title": "Л32",
          "dop": [{"title":"витраж с пескоструйным рисунком"},{"title":"витраж с глубоким матированием"}]
        },
        {
          "title": "Л32-Б",
          "dop": [{"title":"витраж с пескоструйным рисунком"},{"title":"витраж с глубоким матированием"}]
        },
        {
          "title": "Л32-Р",
          "dop": [{"title":"витраж с пескоструйным рисунком"},{"title":"витраж с глубоким матированием"}]
        },
        {
          "title": "Л34",
          "dop": [{"title":"витраж с пескоструйным рисунком"},{"title":"витраж с глубоким матированием"}]
        },
        {
          "title": "Л34-Р",
          "dop": [{"title":"витраж с пескоструйным рисунком"},{"title":"витраж с глубоким матированием"}]
        },
        {
          "title": "Л53",
          "dop": [{"title":"витраж с пескоструйным рисунком"},{"title":"витраж с глубоким матированием"}]
        },
        {
          "title": "Л53-С",
          "dop": [{"title":"витраж с пескоструйным рисунком"},{"title":"витраж с глубоким матированием"}]
        },
        {
          "title": "Л53-С2",
          "dop": [{"title":"витраж с пескоструйным рисунком"},{"title":"витраж с глубоким матированием"}]
        },
        {
          "title": "Л61",
          "dop": [{"title":"витраж с пескоструйным рисунком"},{"title":"витраж с глубоким матированием"}]
        },
        {
          "title": "Л61-Б",
          "dop": [{"title": "витраж на стекле Сатин, 6 мм, с фацетом с двух сторон"},
            {"title":"витраж с пескоструйным рисунком"},{"title":"витраж с глубоким матированием"}]
        },
        {
          "title": "Л61-Б2",
          "dop": [{"title": "витраж на стекле Сатин, 6 мм, с фацетом с двух сторон"},{"title":"витраж с пескоструйным рисунком"},{"title":"витраж с глубоким матированием"}]
        },
        {
          "title": "Л61-Ф",
          "dop": [{"title": "витраж на стекле Сатин, 6 мм, с фацетом с двух сторон"},{"title":"витраж с пескоструйным рисунком"},{"title":"витраж с глубоким матированием"}]
        },
        {
          "title": "Л61-Ф2",
          "dop": [{"title": "витраж на стекле Сатин, 6 мм, с фацетом с двух сторон"},{"title":"витраж с пескоструйным рисунком"},{"title":"витраж с глубоким матированием"}]
        },
        {
          "title": "Л63",
          "dop": [{"title":"витраж с пескоструйным рисунком"},{"title":"витраж с глубоким матированием"}]
        },
        {
          "title": "Л63-А",
          "dop": [{"title":"витраж с пескоструйным рисунком"},{"title":"витраж с глубоким матированием"}]
        },
        {
          "title": "Л63-А2",
          "dop": [{"title":"витраж с пескоструйным рисунком"},{"title":"витраж с глубоким матированием"}]
        },
        {
          "title": "Л21",
          "dop": [{"title":"витраж с пескоструйным рисунком"},{"title":"витраж с глубоким матированием"}]
        },
        {
          "title": "Л22",
          "dop": [{"title":"витраж с пескоструйным рисунком"},{"title":"витраж с глубоким матированием"}]
        },
        {
          "title": "ЛФ10**",
          "dop": [
            {"title":"накладной элемент \"косичка\" на нижней филенке"},
            {"title":"витраж с пескоструйным рисунком"}
          ]
        },
        {
          "title": "ЛФ20**",
          "dop": [{"title":"витраж с пескоструйным рисунком"},{"title":"витраж с глубоким матированием"}]
        }
      ]
    },
    {
      "title": "ЛК",
      "models": [
        "ЛК24",
        "ЛК25*"
      ]
    },
    {
      "title": "ЛН",
      "models": [
        "ЛН31",
        "ЛН33",
        "ЛН16",
        "ЛН21",
        "ЛН40",
        "ЛН41",
        "ЛН42",
        "ЛН43",
        "ЛН44",
        "ЛН70",
        "ЛН71",
        "ЛН72",
        "ЛН73",
        "ЛН70-Ф"
      ]
    },
    {
      "title": "ЛЧ",
      "models": [
        "ЛЧ10",
        " ЛЧ13",
        " ЛЧ53",
        " ЛЧ61",
        " ЛЧ62",
        " ЛЧ80",
        " ЛЧ90",
        " ЛЧ92",
        "ЛЧ10-С",
        " ЛЧ13-С",
        " ЛЧ53-С",
        " ЛЧ53-С2",
        " ЛЧ61-С",
        " ЛЧ61-С2",
        " ЛЧ62-В",
        " ЛЧ80-Р**",
        " ЛЧ91",
        " ЛЧ93"
      ]
    },
    {
      "title": "Л3D",
      "models": [
        "Л3D-21*",
        "Л3D-22*",
        "Л3D-23*",
        "Л3D-25*",
        "Л3D-31*"
      ]
    }
  ]
}